{
	"configurations" : 
	[
		{
			"directories" : 
			[
				{
					"build" : ".",
					"childIndexes" : 
					[
						1
					],
					"hasInstallRule" : true,
					"jsonFile" : "directory-.-Debug-d0094a50bb2071803777.json",
					"minimumCMakeVersion" : 
					{
						"string" : "3.28"
					},
					"projectIndex" : 0,
					"source" : ".",
					"targetIndexes" : 
					[
						0
					]
				},
				{
					"build" : "lib/raylib",
					"childIndexes" : 
					[
						2
					],
					"hasInstallRule" : true,
					"jsonFile" : "directory-lib.raylib-Debug-cba51dfa3f85fcfc0c90.json",
					"minimumCMakeVersion" : 
					{
						"string" : "3.0"
					},
					"parentIndex" : 0,
					"projectIndex" : 1,
					"source" : "lib/raylib",
					"targetIndexes" : 
					[
						3
					]
				},
				{
					"build" : "lib/raylib/raylib",
					"childIndexes" : 
					[
						3
					],
					"hasInstallRule" : true,
					"jsonFile" : "directory-lib.raylib.raylib-Debug-0779a7185080477f5fac.json",
					"minimumCMakeVersion" : 
					{
						"string" : "3.0"
					},
					"parentIndex" : 1,
					"projectIndex" : 1,
					"source" : "lib/raylib/src",
					"targetIndexes" : 
					[
						2
					]
				},
				{
					"build" : "lib/raylib/raylib/external/glfw",
					"childIndexes" : 
					[
						4
					],
					"jsonFile" : "directory-lib.raylib.raylib.external.glfw-Debug-a460328a3dbe35a05d85.json",
					"minimumCMakeVersion" : 
					{
						"string" : "3.4"
					},
					"parentIndex" : 2,
					"projectIndex" : 2,
					"source" : "lib/raylib/src/external/glfw"
				},
				{
					"build" : "lib/raylib/raylib/external/glfw/src",
					"jsonFile" : "directory-lib.raylib.raylib.external.glfw.src-Debug-2d1e1298f10af7745550.json",
					"minimumCMakeVersion" : 
					{
						"string" : "3.4"
					},
					"parentIndex" : 3,
					"projectIndex" : 2,
					"source" : "lib/raylib/src/external/glfw/src",
					"targetIndexes" : 
					[
						1,
						4
					]
				}
			],
			"name" : "Debug",
			"projects" : 
			[
				{
					"childIndexes" : 
					[
						1
					],
					"directoryIndexes" : 
					[
						0
					],
					"name" : "SnakeRaylib",
					"targetIndexes" : 
					[
						0
					]
				},
				{
					"childIndexes" : 
					[
						2
					],
					"directoryIndexes" : 
					[
						1,
						2
					],
					"name" : "raylib",
					"parentIndex" : 0,
					"targetIndexes" : 
					[
						2,
						3
					]
				},
				{
					"directoryIndexes" : 
					[
						3,
						4
					],
					"name" : "GLFW",
					"parentIndex" : 1,
					"targetIndexes" : 
					[
						1,
						4
					]
				}
			],
			"targets" : 
			[
				{
					"directoryIndex" : 0,
					"id" : "SnakeRaylib::@6890427a1f51a3e7e1df",
					"jsonFile" : "target-SnakeRaylib-Debug-89e286b8919c771633a2.json",
					"name" : "SnakeRaylib",
					"projectIndex" : 0
				},
				{
					"directoryIndex" : 4,
					"id" : "glfw::@4e014b6af65fbb183af1",
					"jsonFile" : "target-glfw-Debug-32c265e012074f34cb52.json",
					"name" : "glfw",
					"projectIndex" : 2
				},
				{
					"directoryIndex" : 2,
					"id" : "raylib::@3eed9eed2c1f0ea8aac2",
					"jsonFile" : "target-raylib-Debug-94f74dba616133514156.json",
					"name" : "raylib",
					"projectIndex" : 1
				},
				{
					"directoryIndex" : 1,
					"id" : "uninstall::@674251c4d9a72970adbc",
					"jsonFile" : "target-uninstall-Debug-bfb42d3f3f79a9976eea.json",
					"name" : "uninstall",
					"projectIndex" : 1
				},
				{
					"directoryIndex" : 4,
					"id" : "update_mappings::@4e014b6af65fbb183af1",
					"jsonFile" : "target-update_mappings-Debug-499b7d4dcdfaf975f2df.json",
					"name" : "update_mappings",
					"projectIndex" : 2
				}
			]
		}
	],
	"kind" : "codemodel",
	"paths" : 
	{
		"build" : "X:/Code/C++/SnakeRaylib/cmake-build-debug",
		"source" : "X:/Code/C++/SnakeRaylib"
	},
	"version" : 
	{
		"major" : 2,
		"minor" : 6
	}
}
